odoo10_addon_account_fiscal_position_vat_check-10.0.1.0.0-py2.7-nspkg.pth
odoo10_addon_account_fiscal_position_vat_check-10.0.1.0.0.dist-info/top_level.txt
odoo10_addon_account_fiscal_position_vat_check-10.0.1.0.0.dist-info/WHEEL
odoo10_addon_account_fiscal_position_vat_check-10.0.1.0.0.dist-info/RECORD
odoo10_addon_account_fiscal_position_vat_check-10.0.1.0.0.dist-info/metadata.json
odoo10_addon_account_fiscal_position_vat_check-10.0.1.0.0.dist-info/DESCRIPTION.rst
odoo10_addon_account_fiscal_position_vat_check-10.0.1.0.0.dist-info/METADATA
odoo10_addon_account_fiscal_position_vat_check-10.0.1.0.0.dist-info/namespace_packages.txt
odoo/addons/account_fiscal_position_vat_check/__manifest__.py
odoo/addons/account_fiscal_position_vat_check/__init__.py
odoo/addons/account_fiscal_position_vat_check/README.rst
odoo/addons/account_fiscal_position_vat_check/models/account_invoice.py
odoo/addons/account_fiscal_position_vat_check/models/partner.py
odoo/addons/account_fiscal_position_vat_check/models/__init__.py
odoo/addons/account_fiscal_position_vat_check/i18n/ja.po
odoo/addons/account_fiscal_position_vat_check/i18n/zh_CN.po
odoo/addons/account_fiscal_position_vat_check/i18n/account_fiscal_position_vat_check.pot
odoo/addons/account_fiscal_position_vat_check/i18n/ru.po
odoo/addons/account_fiscal_position_vat_check/i18n/pt.po
odoo/addons/account_fiscal_position_vat_check/i18n/it.po
odoo/addons/account_fiscal_position_vat_check/i18n/es.po
odoo/addons/account_fiscal_position_vat_check/i18n/nl_BE.po
odoo/addons/account_fiscal_position_vat_check/i18n/ar.po
odoo/addons/account_fiscal_position_vat_check/i18n/lt.po
odoo/addons/account_fiscal_position_vat_check/i18n/ro.po
odoo/addons/account_fiscal_position_vat_check/i18n/tr.po
odoo/addons/account_fiscal_position_vat_check/i18n/mk.po
odoo/addons/account_fiscal_position_vat_check/i18n/hr.po
odoo/addons/account_fiscal_position_vat_check/i18n/es_EC.po
odoo/addons/account_fiscal_position_vat_check/i18n/zh_TW.po
odoo/addons/account_fiscal_position_vat_check/i18n/hu.po
odoo/addons/account_fiscal_position_vat_check/i18n/ca.po
odoo/addons/account_fiscal_position_vat_check/i18n/id.po
odoo/addons/account_fiscal_position_vat_check/i18n/es_CR.po
odoo/addons/account_fiscal_position_vat_check/i18n/sl.po
odoo/addons/account_fiscal_position_vat_check/i18n/sr@latin.po
odoo/addons/account_fiscal_position_vat_check/i18n/th.po
odoo/addons/account_fiscal_position_vat_check/i18n/cs.po
odoo/addons/account_fiscal_position_vat_check/i18n/nb.po
